gender_local/__init__.py
gender_local/constants_gender_local.py
gender_local/gender.py
gender_local/gender_enum.py
gender_local-0.0.14.dist-info/METADATA
gender_local-0.0.14.dist-info/WHEEL
gender_local-0.0.14.dist-info/top_level.txt
gender_local-0.0.14.dist-info/RECORD
