Metadata-Version: 2.1
Name: gender-local
Version: 0.0.14
Summary: PyPI Package for Circles gender-local Local/Remote Python
Home-page: https://github.com/circles-zone/gender-local-python-package
Author: Circles
Author-email: info@circlez.ai
Classifier: Programming Language :: Python :: 3
Classifier: License :: Other/Proprietary License
Classifier: Operating System :: OS Independent
Requires-Dist: database-mysql-local
Requires-Dist: logger-local
Requires-Dist: language-remote
